GeoBaseMain.py
LICENSE
MANIFEST.in
README
README.rst
RELEASE_NOTES.rst
VERSION
setup.py
GeoBases/GeoBaseModule.py
GeoBases/GeoUtils.py
GeoBases/SourcesManagerModule.py
GeoBases/__init__.py
GeoBases/DataSources/CheckDataUpdates.sh
GeoBases/DataSources/Sources.yaml
GeoBases/DataSources/Airlines/ori_airlines.csv
GeoBases/DataSources/Airports/GeoNames/README.txt
GeoBases/DataSources/Airports/GeoNames/airports_geonames_only_clean.csv
GeoBases/DataSources/Cabins/cabins.csv
GeoBases/DataSources/Cities/cities15000.zip
GeoBases/DataSources/Continents/continentCodes.txt
GeoBases/DataSources/Countries/README.txt
GeoBases/DataSources/Countries/capitals.csv
GeoBases/DataSources/Countries/countryInfo.txt
GeoBases/DataSources/Currencies/wiki_source_ISO_4217.csv
GeoBases/DataSources/FeatureClasses/feature_classes.csv
GeoBases/DataSources/FeatureCodes/featureCodes_en.txt
GeoBases/DataSources/Languages/iso-languagecodes.txt
GeoBases/DataSources/Locales/locales.csv
GeoBases/DataSources/LocationTypes/location_types.csv
GeoBases/DataSources/Por/GeoNames/FR.zip
GeoBases/DataSources/Por/GeoNames/MC.zip
GeoBases/DataSources/Por/GeoNames/README.txt
GeoBases/DataSources/Por/Ori/ori_por_non_iata.csv
GeoBases/DataSources/Por/Ori/ori_por_public.csv
GeoBases/DataSources/PostalCodes/GeoNames/FR.zip
GeoBases/DataSources/PostalCodes/GeoNames/MC.zip
GeoBases/DataSources/TimeZones/timeZones.txt
GeoBases/DataSources/TrainStations/README.txt
GeoBases/DataSources/TrainStations/DataGouvFr/RFF_gares.ids.gm.man.red.csv
GeoBases/DataSources/TrainStations/NLS/NLS_CODES_RefDataSNCF.csv
GeoBases/DataSources/TrainStations/UIC/sncfExtract_v1.0.csv
GeoBases/GraphAssets/graph.js
GeoBases/GraphAssets/jit-yc.js
GeoBases/GraphAssets/jit.js
GeoBases/GraphAssets/template.html
GeoBases/MapAssets/black_marker.png
GeoBases/MapAssets/black_point.png
GeoBases/MapAssets/blue_marker.png
GeoBases/MapAssets/blue_point.png
GeoBases/MapAssets/cyan_marker.png
GeoBases/MapAssets/cyan_point.png
GeoBases/MapAssets/green_marker.png
GeoBasesPypy.egg-info/PKG-INFO
GeoBasesPypy.egg-info/SOURCES.txt
GeoBasesPypy.egg-info/dependency_links.txt
GeoBasesPypy.egg-info/entry_points.txt
GeoBasesPypy.egg-info/requires.txt
GeoBasesPypy.egg-info/top_level.txt
