Metadata-Version: 1.1
Name: GeoBasesPypy
Version: 5.0.15
Summary: Data services and visualization - Pypy version
Home-page: http://opentraveldata.github.com/geobases
Author: Alex Prengère
Author-email: geobases.dev@gmail.com
License: Creative Commons
